{
    "curves": [
        {
            "control_points": [
                [
                    0.0,
                    -0.45954298973083496,
                    0.0
                ],
                [
                    0.0,
                    -0.45954400300979614,
                    0.0
                ],
                [
                    0.0,
                    -0.45954498648643494,
                    0.0
                ],
                [
                    -0.3518820106983185,
                    -0.42674699425697327,
                    0.0
                ],
                [
                    -0.8486559987068176,
                    -0.2788980007171631,
                    0.0
                ],
                [
                    -1.1120970249176025,
                    0.08400499820709229,
                    0.0
                ],
                [
                    -1.1647850275039673,
                    1.105510950088501,
                    0.0
                ],
                [
                    -0.9916669726371765,
                    2.3286290168762207,
                    0.0
                ],
                [
                    -1.0293010473251343,
                    2.5033600330352783,
                    0.0
                ],
                [
                    -1.0887999534606934,
                    2.345599889755249,
                    0.0
                ],
                [
                    -1.277999997138977,
                    1.1627999544143677,
                    0.0
                ],
                [
                    -1.2148000001907349,
                    0.0551999993622303,
                    0.0
                ],
                [
                    -0.9156000018119812,
                    -0.38119998574256897,
                    0.0
                ],
                [
                    -0.38040000200271606,
                    -0.621999979019165,
                    0.0
                ],
                [
                    -0.14399999380111694,
                    -0.9684000015258789,
                    0.0
                ],
                [
                    -0.09679999947547913,
                    -1.4800000190734863,
                    0.0
                ],
                [
                    -0.12839999794960022,
                    -2.1124000549316406,
                    0.0
                ],
                [
                    -0.3172000050544739,
                    -2.2028000354766846,
                    0.0
                ],
                [
                    -0.9944000244140625,
                    -2.2627999782562256,
                    0.0
                ],
                [
                    -1.2148000001907349,
                    -2.323199987411499,
                    0.0
                ],
                [
                    -1.1992000341415405,
                    -2.398400068283081,
                    0.0
                ],
                [
                    -1.0576000213623047,
                    -2.4588000774383545,
                    0.0
                ],
                [
                    -0.7111999988555908,
                    -2.4588000774383545,
                    0.0
                ],
                [
                    0.0,
                    -2.4588000774383545,
                    0.0
                ],
                [
                    0.0,
                    -2.458801031112671,
                    0.0
                ],
                [
                    0.0,
                    -2.4588019847869873,
                    0.0
                ]
            ],
            "type": "bspline"
        }
    ],
    "surfaces": [
        {
            "curve_indices": [
                0
            ],
            "type": "revolution"
        }
    ]
}